{
  "005930.KS": {
    "name": "삼성전자",
    "code": "005930.KS",
    "added_date": "2025-06-17T14:33:10.811077",
    "last_updated": "2025-09-19T02:37:55.236130",
    "current_price": 80300.0,
    "recent_high": 80500.0,
    "recent_high_date": "2025-09-18",
    "decline_rate": 0.2484472049689441,
    "error_message": null
  },
  "000660.KS": {
    "name": "SK하이닉스",
    "code": "000660.KS",
    "added_date": "2025-06-17T22:25:33.092380",
    "last_updated": "2025-09-19T02:37:55.409549",
    "current_price": 355500.0,
    "recent_high": 357000.0,
    "recent_high_date": "2025-09-18",
    "decline_rate": 0.42016806722689076,
    "error_message": null
  },
  "035420.KS": {
    "name": "NAVER",
    "code": "035420.KS",
    "original_code": "035420.KS",
    "added_date": "2025-06-17T22:34:09.813135",
    "last_updated": "2025-09-19T02:37:55.673643",
    "current_price": 236750.0,
    "recent_high": 295000.0,
    "recent_high_date": "2025-06-23",
    "decline_rate": 19.745762711864405,
    "error_message": null,
    "market_type": "KRX"
  },
  "AAPL": {
    "name": "Apple",
    "code": "AAPL",
    "original_code": "AAPL",
    "added_date": "2025-06-17T22:37:51.045863",
    "last_updated": "2025-09-19T02:37:55.884375",
    "current_price": 237.8800048828125,
    "recent_high": 241.32000732421875,
    "recent_high_date": "2025-09-05",
    "decline_rate": 1.4254940895905621,
    "error_message": null,
    "market_type": "US"
  },
  "MSFT": {
    "name": "Microsoft",
    "code": "MSFT",
    "original_code": "MSFT",
    "added_date": "2025-06-17T22:39:17.489681",
    "last_updated": "2025-09-19T02:37:56.072146",
    "current_price": 508.45001220703125,
    "recent_high": 554.5383762548963,
    "recent_high_date": "2025-07-31",
    "decline_rate": 8.311122551900777,
    "error_message": null,
    "market_type": "US"
  }
}